aonet/__init__.py
aonet/aonet.py
aonet-1.0.4.dist-info/METADATA
aonet-1.0.4.dist-info/WHEEL
aonet-1.0.4.dist-info/top_level.txt
aonet-1.0.4.dist-info/RECORD
