Metadata-Version: 2.1
Name: aonet
Version: 1.0.4
Summary: aonet python SDK
Author: 
Author-email: 
Requires-Dist: http.client
